fastjwtapi/__init__.py
fastjwtapi/auth.py
fastjwtapi/core.py
fastjwtapi/dependency.py
fastjwtapi/middlewares.py
test/__init__.py
fastjwtapi-0.0.6.dist-info/LICENSE
fastjwtapi-0.0.6.dist-info/METADATA
fastjwtapi-0.0.6.dist-info/WHEEL
fastjwtapi-0.0.6.dist-info/top_level.txt
fastjwtapi-0.0.6.dist-info/RECORD
