Metadata-Version: 2.1
Name: fastjwtapi
Version: 0.0.6
Summary: An add-on for the FastAPI framework that makes it easier to work with JWT authorization.
Home-page: https://github.com/lengthylyova/fastjwtapi/
Author: lengthylyova
Author-email: lengthylyova@gmail.com
License: MIT
License-File: LICENSE
Requires-Dist: PyJWT >=2.8.0
Requires-Dist: fastapi >=0.111.1
Requires-Dist: SQLAlchemy >=2.0.31
Provides-Extra: dev
Requires-Dist: twine >=5.1.1 ; extra == 'dev'
